[
  {
    "id": 1,
    "name": "Subhajit Ghosh",
    "email": "subhajitghosh@gmail.com",
    "password": "Subhajit704@"           ,
    "age": 22,
    "phone": 8927592853,
    "dob": "2022-05-14",
    "senior": "Souvik Mondal",
    "salary": 30000,
    "communicationaddress": "Kolkata",
    "permanentaddress": "Karanda",
    "gender": "Male",
    "designation": "Frontend Developer",
    "usertype": "Admin",
    "photo": "https://www.linkpicture.com/q/subhajit.jpg"
  },
  {
    "id": 2,
    "name": "Raj Chowdhury",
    "email": "srajcho3892@gmail.com",
    "password": "Razz704@"           ,
    "age": 22,
    "phone": 8927592854,
    "dob": "2022-05-14",
    "senior": "Souvik Mondal",
    "salary": 31000,
    "communicationaddress": "Kolkata",
    "permanentaddress": "Karanda",
    "gender": "Male",
    "designation": "Frontend Developer",
    "usertype": "Admin",
    "photo": "https://www.linkpicture.com/q/1656351400274.jpg"
  },
  {
    "id": 3,
    "name": "Atanu Mondal",
    "email": "atanu@gmail.com",
    "password": "Atanu704@"           ,
    "age": 21,
    "phone": 8927592854,
    "dob": "2022-05-14",
    "senior": "Souvik Mondal",
    "salary": 28000,
    "communicationaddress": "Kolkata",
    "permanentaddress": "Karanda",
    "gender": "Male",
    "designation": "Frontend Developer",
    "usertype": "User",
    "photo": "https://www.linkpicture.com/q/IMG-20220627-WA0024.jpg"
  },
  {
    "id": 4,
    "name": "Mojimun Islam",
    "email": "mojimun@gmail.com",
    "password": "Mojimun704@"           ,
    "age": 21,
    "phone": 8927592859,
    "dob": "2022-05-14",
    "senior": "Souvik Mondal",
    "salary": 30000,
    "communicationaddress": "Kolkata",
    "permanentaddress": "Karanda",
    "gender": "Male",
    "designation": "Frontend Developer",
    "usertype": "User",
    "photo": "https://www.linkpicture.com/q/IMG-20220627-WA0014_1.jpg"
  },
  {
    "id": 5,
    "name": "Haranath Chakraborty",
    "email": "haranath@gmail.com",
    "password": "Hara704@"           ,
    "age": 20,
    "phone": 8927592899,
    "dob": "2022-05-14",
    "senior": "Souvik Mondal",
    "salary": 28000,
    "communicationaddress": "Kolkata",
    "permanentaddress": "Karanda",
    "gender": "Male",
    "designation": "Frontend Developer",
    "usertype": "User",
    "photo": "https://www.linkpicture.com/q/IMG-20220627-WA0012_3.jpg"
  },
  {
    "id": 6,
    "name": "Sujay Negel",
    "email": "sujay@gmail.com",
    "password": "Sujay704@"           ,
    "age": 25,
    "phone": 8927592999,
    "dob": "2022-05-14",
    "senior": "Mijanur Rahaman",
    "salary": 29000,
    "communicationaddress": "Kolkata",
    "permanentaddress": "Karanda",
    "gender": "Male",
    "designation": "Frontend Developer",
    "usertype": "User",
    "photo": "https://www.linkpicture.com/q/IMG-20220627-WA0013_3.jpg"
  },
  {
    "id": 7,
    "name": "Koustav Das",
    "email": "Koustav@gmail.com",
    "password": "Koustav704@"           ,
    "age": 25,
    "phone": 8924592999,
    "dob": "2022-05-14",
    "senior": "Mijanur Rahaman",
    "salary": 29000,
    "communicationaddress": "Kolkata",
    "permanentaddress": "Karanda",
    "gender": "Male",
    "designation": "Frontend Developer",
    "usertype": "User",
    "photo": "https://www.linkpicture.com/q/IMG-20220627-WA0016.jpg"
  },
  {
    "id": 8,
    "name": "Ratnadeep Dey",
    "email": "Ratnadeep@gmail.com",
    "password": "Ratna704@"           ,
    "age": 24,
    "phone": 8924592999,
    "dob": "1998-11-17",
    "senior": "Mijanur Rahaman",
    "salary": 29000,
    "communicationaddress": "Kolkata",
    "permanentaddress": "BudBud, District-Burdwan",
    "gender": "Male",
    "designation": "Frontend Developer",
    "usertype": "User",
    "photo": "https://www.linkpicture.com/q/DSC_0059-1-2.jpg"
  },
  {
    "id": 9,
    "name": "Suchitra Bhattacharya",
    "email": "suchitra@gmail.com",
    "password": "Subh704@"           ,
    "age": 26,
    "phone": 8924592999,
    "dob": "2022-05-14",
    "senior": "Mijanur Rahaman",
    "salary": 26000,
    "communicationaddress": "Kolkata",
    "permanentaddress": "Karanda",
    "gender": "Female",
    "designation": "Frontend Developer",
    "usertype": "User",
    "photo": "https://www.linkpicture.com/q/IMG-20220627-WA0018.jpg"
  },
  {
    "id": 10,
    "name": "Suchitra Das",
    "email": "das@gmail.com",
    "password": "Suchitra704@"           ,
    "age": 26,
    "phone": 8924592999,
    "dob": "2022-05-14",
    "senior": "Mijanur Rahaman",
    "salary": 29000,
    "communicationaddress": "Kolkata",
    "permanentaddress": "Karanda",
    "gender": "Female",
    "designation": "Frontend Developer",
    "usertype": "User",
    "photo": "https://www.linkpicture.com/q/IMG-20220627-WA0019.jpg"
  },
  {
    "id": 11,
    "name": "Risha Bhattacharya",
    "email": "risha@gmail.com",
    "password": "Risha704@"           ,
    "age": 26,
    "phone": 8924092999,
    "dob": "2022-05-14",
    "senior": "Mijanur Rahaman",
    "salary": 29000,
    "communicationaddress": "Kolkata",
    "permanentaddress": "Karanda",
    "gender": "Female",
    "designation": "Frontend Developer",
    "usertype": "User",
    "photo": "https://www.linkpicture.com/q/IMG-20220627-WA0032_1.jpg"
  }
]